{
  "Présent": [
    "J'avale mon café trop vite le matin.",
    "Tu avales ta nourriture sans mâcher.",
    "Il avale un comprimé avec un verre d'eau.",
    "Nous avalons nos sandwichs sur le pouce.",
    "Elles avalent difficilement la pilule amère de l'échec."
  ],
  "Imparfait": [
    "J'avalais mes repas en regardant les nouvelles.",
    "Tu avalais tout ce qu'on te disait sans te poser de questions.",
    "Elle avalait ses médicaments avec du jus d'orange.",
    "Nous avalions des kilomètres sur l'autoroute.",
    "Ils avalaient les rebuffades sans broncher."
  ],
  "Futur Simple": [
    "J'avalerai ce médicament après le dîner.",
    "Tu avaleras ta fierté et tu t'excuseras.",
    "Il avalera les couleuvres s'il le faut.",
    "Nous avalerons des kilomètres pour arriver à temps.",
    "Elles avaleront la nouvelle avec peine."
  ],
  "Passé Composé": [
    "J'ai avalé de travers et j'ai toussé.",
    "Tu as avalé cette information sans vérifier.",
    "Elle a avalé son repas avant de partir.",
    "Nous avons avalé bien des couleuvres depuis le début.",
    "Ils ont avalé la pilule malgré leur mécontentement."
  ],
  "Futur Proche": [
    "Je vais avaler ce cachet contre la migraine.",
    "Tu vas avaler tes paroles si tu n'y prends pas garde.",
    "Il va avaler sa soupe avant de sortir.",
    "Nous allons avaler des kilomètres ce week-end.",
    "Elles vont avaler la nouvelle sans sourciller."
  ],
  "Passé Récent": [
    "Je viens d'avaler un verre d'eau froide.",
    "Tu viens d'avaler la nouvelle sans réagir.",
    "Elle vient d'avaler son petit-déjeuner en vitesse.",
    "Nous venons d'avaler les derniers kilomètres du trajet.",
    "Ils viennent d'avaler une couleuvre de taille."
  ],
  "Impératif": [
    "Avale ce médicament avant de dormir.",
    "Avalons ce repas rapidement et partons.",
    "Avalez votre orgueil et présentez vos excuses.",
    "N'avale pas si vite, tu vas t'étouffer.",
    "Avalez ces nouvelles avec philosophie."
  ],
  "Conditionnel Présent": [
    "J'avalerais n'importe quoi si j'avais faim.",
    "Tu avalerais mieux ce comprimé avec de l'eau.",
    "Il avalerait des kilomètres pour la voir.",
    "Nous avalerions cette décision si on nous expliquait pourquoi.",
    "Elles avaleraient la pilule si elles n'avaient pas le choix."
  ]
}
